voicecrypt/__init__.py
voicecrypt/core.py
voicecrypt-0.1.0.dist-info/METADATA
voicecrypt-0.1.0.dist-info/WHEEL
voicecrypt-0.1.0.dist-info/top_level.txt
voicecrypt-0.1.0.dist-info/RECORD
