Metadata-Version: 2.4
Name: voicecrypt
Version: 0.1.0
Summary: Encrypt and decrypt audio files as text for secure voice messaging.
Author-email: Your Name <your@email.com>
Requires-Python: >=3.7
Requires-Dist: cryptography>=41.0.0
